{
  "naive_S5": [],
  "psl2_5": [
    {
      "signs": [
        1,
        1,
        1,
        1,
        1,
        1,
        1
      ],
      "orbit": [
        1
      ],
      "H_size": 60
    },
    {
      "signs": [
        1,
        1,
        -1,
        -1,
        1,
        1,
        1
      ],
      "orbit": [
        1
      ],
      "H_size": 60
    },
    {
      "signs": [
        -1,
        1,
        1,
        1,
        1,
        -1,
        1
      ],
      "orbit": [
        1
      ],
      "H_size": 60
    },
    {
      "signs": [
        -1,
        1,
        -1,
        -1,
        1,
        -1,
        1
      ],
      "orbit": [
        1
      ],
      "H_size": 60
    }
  ]
}