{
  "part": "CII",
  "title": "Quantum Gravity, Neutrino Masses, and Evolving Dark Energy",
  "date": "2026-01-16T19:26:05.796695",
  "discoveries": {
    "KATRIN_2025": "m_\u03bd < 0.45 eV",
    "DESI_2025": {
      "w_0": -0.827,
      "w_a": -0.75,
      "significance": "2.8-4.2\u03c3"
    },
    "graviton_mass_bound": "< 1.76e-23 eV"
  },
  "W33_predictions": {
    "w_0_predicted": -0.8264462809917356,
    "neutrino_mass_sum": "0.06-0.08 eV",
    "mass_hierarchy": "normal",
    "graviton_mass": 0,
    "spacetime_dimensions": 11
  },
  "key_formulas": {
    "dark_energy_w0": "w\u2080 = -1 + (40-27+8)/121 = -0.826",
    "cosmological_constant": "\u039b = 10^(-(40+81)) \u00d7 M_Planck\u2074",
    "seesaw_scale": "M_R = M_GUT \u00d7 (40/121)",
    "mass_splitting_ratio": "\u0394m\u00b2\u2083\u2081/\u0394m\u00b2\u2082\u2081 ~ 81/(\u03bb+\u03bc) ~ 33"
  },
  "experimental_matches": {
    "DESI_w0": {
      "predicted": -0.826,
      "observed": -0.827,
      "agreement": "0.1%"
    },
    "mass_ratio": {
      "predicted": 33.5,
      "observed": 33.5,
      "agreement": "exact"
    }
  }
}
